AUTHORS.rst
CHANGELOG.rst
MANIFEST.in
README.rst
TODO.rst
netscaler.py
setup.py
docs/Makefile
docs/api.rst
docs/changelog.rst
docs/conf.py
docs/index.rst
docs/license.rst
docs/make.bat
examples/NSUserAdmin.wsdl
examples/all_commands.txt
examples/nsuser.py
netscaler_api.egg-info/PKG-INFO
netscaler_api.egg-info/SOURCES.txt
netscaler_api.egg-info/dependency_links.txt
netscaler_api.egg-info/requires.txt
netscaler_api.egg-info/top_level.txt