Metadata-Version: 1.1
Name: netscaler-api
Version: 0.2.3
Summary: NetScaler API is a Python interface for interacting with Citrix NetScaler application delivery controllers, utilizing the SOAP API to execute commands.
Home-page: http://github.com/jathanism/netscaler-api/
Author: Jathan McCollum
Author-email: jathan@gmail.com
License: BSD
Keywords: Networking,Automation,library,Security,NetScaler,API,SOAP
Platform: UNKNOWN
Classifier: Development Status :: 3 - Alpha
Classifier: Environment :: Console
Classifier: Intended Audience :: Developers
Classifier: Intended Audience :: Information Technology
Classifier: Intended Audience :: Science/Research
Classifier: Intended Audience :: System Administrators
Classifier: Intended Audience :: Telecommunications Industry
Classifier: Natural Language :: English
Classifier: License :: OSI Approved :: BSD License
Classifier: Operating System :: OS Independent
Classifier: Programming Language :: Python
Classifier: Topic :: Education :: Testing
Classifier: Topic :: Internet
Classifier: Topic :: Security
Classifier: Topic :: Software Development
Classifier: Topic :: Software Development :: Libraries :: Python Modules
Classifier: Topic :: System :: Networking
Classifier: Topic :: System :: Networking :: Monitoring
Classifier: Topic :: System :: Operating System
Classifier: Topic :: System :: Systems Administration
Classifier: Topic :: Utilities
